CHANGELOG.rst
COPYRIGHT.rst
LICENSE
MANIFEST.in
README
README.rst
setup.cfg
setup.py
doc/ExtendedRequestsLibrary.html
src/ExtendedRequestsLibrary/__init__.py
src/ExtendedRequestsLibrary/version.py
src/ExtendedRequestsLibrary/keywords/__init__.py
src/ExtendedRequestsLibrary/keywords/utility.py
src/robotframework_extendedrequestslibrary.egg-info/PKG-INFO
src/robotframework_extendedrequestslibrary.egg-info/SOURCES.txt
src/robotframework_extendedrequestslibrary.egg-info/dependency_links.txt
src/robotframework_extendedrequestslibrary.egg-info/pbr.json
src/robotframework_extendedrequestslibrary.egg-info/requires.txt
src/robotframework_extendedrequestslibrary.egg-info/top_level.txt