Metadata-Version: 1.1
Name: robotframework-extendedrequestslibrary
Version: 0.5.3
Summary: Extended HTTP client testing library for Robot Framework with OAuth2 support
Home-page: https://github.com/rickypc/robotframework-extendedrequestslibrary
Author: Richard Huang
Author-email: rickypc@users.noreply.github.com
License: AGPL 3
Keywords: robot framework extended http testing automation requests oauth2 oauth rest api softwaretesting
Platform: any
Classifier: Development Status :: 4 - Beta
Classifier: Intended Audience :: Developers
Classifier: Topic :: Software Development :: Testing
Classifier: License :: OSI Approved :: GNU Affero General Public License v3
Classifier: Programming Language :: Python :: 2.7
